Workbook

Sheet MERCADO OBJETIVO
A4: MERCADO POTENCIAL (1) | B4: SJL | C4: 1340000
A5: Edad 18 a 60 años | B5: 0.7 | C5: =C4*B5 -> 938000
A6: NSE B y C | B6: 0.6 | C6: =C5*B6 -> 562800
A7: Preferencia por consumir productos ecoamigables (2) | B7: 0.2 | C7: =C6*B7 -> 112560
A8: MERCADO DISPONIBLE (3)
A9: ¿compra carteras grandes? | B9: 0.1 | C9: =C7*B9 -> 11256
A10: MERCADO EFECTIVO
A11: ¿Consumiria mi producto? | B11: 0.7 | C11: =C9*B11 -> 7879.2
A12: MERCADO OBJETIVO
A15: A qué porcentaje puedo atender | B15: 0.05 | C15: =C11*B15 -> 393.96
A16: (1) Censo INEI
A17: (2) RPP. Entrevista al Ing. Fulano de Tal
A18: (3) Entrevistas realizadas a vendedores de carteras

Sheet COSTO UNITARIO
A3: LA PRODUCCIÓN ESTÁ DE ACUERDO CON LA DEMANDA O UNIDADES PROYECTADAS A VENDER
A4: COSTO DE PRODUCCIÓN
A5: INSUMOS/ PROCESOS NECESARIOS | B5: Cantidad a consumir por unidad | C5: Unidad de medida | D5: Costo en S/. por unidad de medida | E5: Costo Unitario en S/.
A6: Bambu | B6: 3 | C6: mt | D6: 10 | E6: =+B6*D6 -> 30
A7: Adornos | B7: 3 | C7: unidad | D7: 12 | E7: =+B7*D7 -> 36
A8: Tintes Naturales | B8: 0.5 | C8: unidad | D8: 8 | E8: =+D8*B8 -> 4
A9: Correas | B9: 1.5 | C9: mt | D9: 7 | E9: =+B9*D9 -> 10.5
A10: Pegamentos | B10: 0.3 | C10: lt | D10: 6 | E10: =+B10*D10 -> 1.8
A11: Hilos | B11: 1 | C11: unidad | D11: 2.5 | E11: =+B11*D11 -> 2.5
A12: Agujas | B12: 3 | C12: unidad | D12: 1 | E12: =+B12*D12/5 -> 0.6
A13: Botones | B13: 6 | C13: unidad | D13: 0.3 | E13: =+B13*D13/5 -> 0.36
A16: TOTAL MATERIA PRIMA | E16: =+SUM(E6:E15) -> 85.76
A17: Mano de obra | E17: 16.67
A18: COSTO UNITARIO DE CARTERA ECOLÓGICA | E18: =+E16+E17 -> 102.43

Sheet 6.1 INVERSION TOTAL
A2: 6.1 ESTRUCTURA DE INVERSION TOTAL
A3: INVERSION TOTAL | D3: =D4+D19+D28 -> 19080
A4: I. INVERSION FIJA | D4: =D5+D13 -> 5840
A5: INVERSION FIJA TANGIBLE | D5: =SUM(D6:D12) -> 5010
A6: Escritorio | B6: 2 | C6: 300 | D6: =B6*C6 -> 600
A7: Sillas | B7: 2 | C7: 50 | D7: =B7*C7 -> 100
A8: Computadoras | B8: 2 | C8: 1800 | D8: =B8*C8 -> 3600
A9: Servidores | B9: 1 | C9: 380 | D9: =B9*C9 -> 380
A10: Ventilador | B10: 2 | C10: 50 | D10: =B10*C10 -> 100
A11: Productos de limpieza | B11: 3 | C11: 30 | D11: =B11*C11 -> 90
A12: Internet (módem/router) | B12: 1 | C12: 140 | D12: =B12*C12 -> 140
A13: INVERSION FIJA INTANGIBLE | D13: =D14+D15+D16+D17+D18 -> 830
A14: Gastos notariales | B14: 1 | C14: 170 | D14: =C14*B14 -> 170
A15: Hosting y Dominio | B15: 1 | C15: 100 | D15: =C15*B15 -> 100
A16: Licencia de funcionamiento | B16: 1 | C16: 120 | D16: =C16*B16 -> 120
A17: Licencias de Software Base | B17: 1 | C17: 200 | D17: =C17*B17 -> 200
A18: Legalizaciones | B18: 3 | C18: 80 | D18: =C18*B18 -> 240
A19: II. CAPITAL DE TRABAJO | D19: =D20+D22+D26 -> 12890
A20: REALIZABLES | D20: =D21 -> 8000
A21: Materia prima e insumos (Relevantes y Requeridos) | B21: 1 | C21: 8000 | D21: =C21*B21 -> 8000
A22: DISPONIBLES | D22: =SUM(D23:D25) -> 3890 | F22: =D23+D25+D24 -> 3890
A23: Bienes | B23: 1 | C23: ='6.2 ESTRUCTURA DE GASTOS'!C9 -> 380 | D23: =C23*B23 -> 380
A24: Servicios | B24: 1 | C24: ='6.2 ESTRUCTURA DE GASTOS'!C17 -> 480 | D24: =C24*B24 -> 480
A25: Planilla | B25: 1 | C25: ='6.2 ESTRUCTURA DE GASTOS'!C25 -> 3030 | D25: =C25*B25 -> 3030
A26: EXIGIBLE | D26: =D27 -> 1000
A27: Garantía | B27: 1 | C27: 1000 | D27: =C27*B27 -> 1000
A28: III. IMPREVISTOS | D28: 350
A29: Caja chica | B29: 1 | C29: 350 | D29: 350
A32: INVERSION TOTAL | D32: =D33+D36+D40 -> 19080
A33: I. INVERSION FIJA | D33: =SUM(D34,D35) -> 5840
A34: INVERSION FIJA TANGIBLE | D34: =D5 -> 5010
A35: INVERSION FIJA INTANGIBLE | D35: =D13 -> 830
A36: II. CAPITAL DE TRABAJO | D36: =D37+D38+D39 -> 12890
A37: REALIZABLES | D37: =D20 -> 8000
A38: DISPONIBLES | D38: =D22 -> 3890
A39: EXIGIBLE | D39: =D26 -> 1000
A40: III. IMPREVISTOS | D40: =D28 -> 350

Sheet 6.2 ESTRUCTURA DE GASTOS
B2: 6.2 ESTRUCTURA DE COSTOS Y GASTOS
B4: GASTOS ADMINISTRATIVOS EN ADQUISICIÓN DE BIENES
B5: - BIENES | C5: ENE | D5: FEB | E5: MAR | F5: ABRIL | G5: MAY | H5: JUN | I5: JUL | J5: AGO | K5: SET | L5: OCT | M5: NOV | N5: DIC
B6: Materiales de oficina | C6: 120 | D6: 0 | E6: 0 | F6: 0 | G6: 120 | H6: 0 | I6: 0 | J6: 0 | K6: 120 | L6: 0 | M6: 0 | N6: 0 | O6: =SUM(C6:N6) -> 360
B7: Materiales de limpieza (cada 3 meses) | C7: 120 | D7: 0 | E7: 0 | F7: 120 | G7: 120 | H7: 0 | I7: 120 | J7: 0 | K7: 0 | L7: 120 | M7: 120 | N7: 0 | O7: =SUM(C7:N7) -> 720
B8: Materiales de computación | C8: 140 | D8: 140 | E8: 140 | F8: 140 | G8: 0 | H8: 140 | I8: 0 | J8: 140 | K8: 140 | L8: 0 | M8: 140 | N8: 140 | O8: =SUM(D8+C8+E8+F8+H8+J8+K8+M8+N8+L8) -> 1260
B9: GASTO TOTAL EN BIENES | C9: =SUM(C6:C8) -> 380 | D9: =SUM(D6:D8) -> 140 | E9: =SUM(E6:E8) -> 140 | F9: =SUM(F6:F8) -> 260 | G9: =SUM(G6:G8) -> 240 | H9: =SUM(H6:H8) -> 140 | I9: =SUM(I6:I8) -> 120 | J9: =SUM(J6:J8) -> 140 | ... N9: =SUM(N6:N8) -> 140 | O9: =SUM(C9:N9) -> 2340
B11: GASTOS ADMINISTRATIVOS EN ADQUISICIÓN DE SERVICIOS
B12: -SERVICIOS | C12: ENE | D12: FEB | E12: MAR | F12: ABRIL | G12: MAY | H12: JUN | I12: JUL | J12: AGO | K12: SET | L12: OCT | M12: NOV | N12: DIC
B13: Luz | C13: 100 | D13: 100 | E13: 100 | F13: 100 | G13: 100 | H13: 100 | I13: 100 | J13: 100 | K13: 100 | L13: 100 | M13: 100 | N13: 100 | O13: =SUM(C13:N13) -> 1200
B14: Agua | C14: 30 | D14: 30 | E14: 30 | F14: 30 | G14: 30 | H14: 30 | I14: 30 | J14: 30 | K14: 30 | L14: 30 | M14: 30 | N14: 30 | O14: =SUM(C14:N14) -> 360
B15: Teléfono e Internet | C15: 100 | D15: 100 | E15: 100 | F15: 100 | G15: 100 | H15: 100 | I15: 100 | J15: 100 | K15: 100 | L15: 100 | M15: 100 | N15: 100 | O15: =SUM(C15:N15) -> 1200 | Q15: =C9+N17+M25 -> 3920
B16: Alquiler de local* | C16: 250 | D16: 280 | E16: 280 | F16: 280 | G16: 280 | H16: 280 | I16: 280 | J16: 280 | K16: 280 | L16: 280 | M16: 280 | N16: 280 | O16: =SUM(C16:N16) -> 3330
B17: GASTO TOTAL EN SERVICIOS | C17: =SUM(C13:C16) -> 480 | D17: =SUM(D13:D16) -> 510 | E17: =SUM(E13:E16) -> 510 | F17: =SUM(F13:F16) -> 510 | G17: =SUM(G13:G16) -> 510 | H17: =SUM(H13:H16) -> 510 | I17: =SUM(I13:I16) -> 510 | J17: =SUM(J13:J16) -> 510 | ... N17: =SUM(N13:N16) -> 510 | O17: =SUM(C17:N17) -> 6090
B19: GASTOS ADMINISTRATIVOS - PLANILLA DE SUELDOS
B20: CONCEPTO | C20: ENE | D20: FEB | E20: MAR | F20: ABRIL | G20: MAY | H20: JUN | I20: JUL | J20: AGO | K20: SET | L20: OCT | M20: NOV | N20: DIC
B21: CEO/Gerente General | C21: 1015 | D21: 1015 | E21: 1015 | F21: 1015 | G21: 1015 | H21: 1015 | I21: 1015 | J21: 1015 | K21: 1015 | L21: 1015 | M21: 1015 | N21: 1015 | O21: =SUM(C21:N21) -> 12180
B22: Ingeniero Software Senior | C22: 1015 | D22: 1015 | E22: 1015 | F22: 1015 | G22: 1015 | H22: 1015 | I22: 1015 | J22: 1015 | K22: 1015 | L22: 1015 | M22: 1015 | N22: 1015 | O22: =SUM(C22:N22) -> 12180
A23: 0.05 | B23: Contador part-time | C23: 500 | D23: 500 | E23: 500 | F23: 500 | G23: 500 | H23: 500 | I23: 500 | J23: 500 | K23: 500 | L23: 500 | M23: 500 | N23: 500 | O23: =SUM(C23:N23) -> 6000
B24: Marketing part-time | C24: 500 | D24: 500 | E24: 500 | F24: 500 | G24: 500 | H24: 500 | I24: 500 | J24: 500 | K24: 500 | L24: 500 | M24: 500 | N24: 500 | O24: =SUM(C24:N24) -> 6000
B25: TOTAL SUELDOS /mes | C25: =SUM(C21:C24) -> 3030 | D25: =SUM(D21:D24) -> 3030 | E25: =SUM(E21:E24) -> 3030 | F25: =SUM(F21:F24) -> 3030 | G25: =SUM(G21:G24) -> 3030 | H25: =SUM(H21:H24) -> 3030 | I25: =SUM(I21:I24) -> 3030 | J25: =SUM(J21:J24) -> 3030 | ... N25: =SUM(N21:N24) -> 3030 | O25: =SUM(C25:N25) -> 36360
D30: CF | E30: Promedio Mensual | F30: Anual
D31: Bienes | E31: =F31/12 -> 195 | F31: =O9 -> 2340
D32: Servicios | E32: =F32/12 -> 507.5 | F32: =O17 -> 6090
D33: Planilla | E33: =F33/12 -> 3030 | F33: =O25 -> 36360
E34: =SUM(E31:E33) -> 3732.5 | F34: =SUM(F31:F33) -> 44790
C36: 2026 | D36: 2027 | E36: 2028
B37: Gastos Administrativos Proyectados | C37: =F34 -> 44790 | D37: =C37*1.03 -> 46133.7 | E37: =D37*1.03 -> 47517.711

Sheet 6.3 PRESUPUESTO DE INGRESOS
B2: Cuadro 6.3 PRESUPUESTO DE INGRESOS
H3: x
B4: PRESUPUESTO DE INGRESOS AÑO 2026
B5: 0.18 | C5: Enero | D5: Febrero | E5: Marzo | F5: Abril | G5: Mayo | H5: Junio | I5: Julio | J5: Agosto | K5: Set | L5: Octubre | M5: Nov | N5: Dici | O5: Año 1
B6: Unidades | C6: 80 | D6: 80 | E6: 80 | F6: 80 | G6: 80 | H6: 80 | I6: 80 | J6: 80 | K6: 80 | L6: 80 | M6: 80 | N6: 80 | O6: =C6*12 -> 960
B7: Precio unitario (S/30) | C7: =C6*30 -> 2400 | D7: =D6*30 -> 2400 | E7: =E6*30 -> 2400 | F7: =F6*30 -> 2400 | G7: =G6*30 -> 2400 | H7: =H6*30 -> 2400 | I7: =I6*30 -> 2400 | J7: =J6*30 -> 2400 | ... N7: =N6*30 -> 2400 | O7: =C7*12 -> 28800
B8: Clientes con Plan Premium 15% | C8: =C6*0.15 -> 12 | D8: =D6*0.15 -> 12 | E8: =E6*0.15 -> 12 | F8: =F6*0.15 -> 12 | G8: =G6*0.15 -> 12 | H8: =H6*0.15 -> 12 | I8: =I6*0.15 -> 12 | J8: =J6*0.15 -> 12 | ... N8: =N6*0.15 -> 12
B9: Plan Premium (Premium) S/28 | C9: =C8*28 -> 336 | D9: =D8*28 -> 336 | E9: =E8*28 -> 336 | F9: =F8*28 -> 336 | G9: =G8*28 -> 336 | H9: =H8*28 -> 336 | I9: =I8*28 -> 336 | J9: =J8*28 -> 336 | ... N9: =N8*28 -> 336 | O9: =C9*12 -> 4032 | Q9: 100 * 0.15
B10: Porcentaje de clientes personalizados 10% | C10: =C6*0.1 -> 8 | D10: =D6*0.1 -> 8 | E10: =E6*0.1 -> 8 | F10: =F6*0.1 -> 8 | G10: =G6*0.1 -> 8 | H10: =H6*0.1 -> 8 | I10: =I6*0.1 -> 8 | J10: =J6*0.1 -> 8 | ... N10: =N6*0.1 -> 8 | O10: =SUM(C10:N10) -> 96
B11: Personalizacion (S/150) | C11: =C10*150 -> 1200 | D11: =D10*150 -> 1200 | E11: =E10*150 -> 1200 | F11: =F10*150 -> 1200 | G11: =G10*150 -> 1200 | H11: =H10*150 -> 1200 | I11: =I10*150 -> 1200 | J11: =J10*150 -> 1200 | ... N11: =N10*150 -> 1200 | O11: =SUM(C11:N11) -> 14400
B12: Renovación anual de licencia S/190 | C12: =C6*0.15*190/1.8 -> 1266.6667 | D12: =D6*0.15*190/1.8 -> 1266.6667 | E12: =E6*0.15*190/1.8 -> 1266.6667 | F12: =F6*0.15*190/1.8 -> 1266.6667 | G12: =G6*0.15*190/1.8 -> 1266.6667 | H12: =H6*0.15*190/1.8 -> 1266.6667 | I12: =I6*0.15*190/1.8 -> 1266.6667 | J12: =J6*0.15*190/1.8 -> 1266.6667 | ... N12: =N6*0.15*190/1.8 -> 1266.6667 | O12: =C12*12 -> 15200
B13: Tasa de Penetración (Soporte S/ 100) | C13: =C6*0.1*100/1.2 -> 666.66667 | D13: =D6*0.1*100/1.2 -> 666.66667 | E13: =E6*0.1*100/1.2 -> 666.66667 | F13: =F6*0.1*100/1.2 -> 666.66667 | G13: =G6*0.1*100/1.2 -> 666.66667 | H13: =H6*0.1*100/1.2 -> 666.66667 | I13: =I6*0.1*100/1.2 -> 666.66667 | J13: =J6*0.1*100/1.2 -> 666.66667 | ... N13: =N6*0.1*100/1.2 -> 666.66667 | O13: =C13*12 -> 8000
B14: Ingresos | C14: =SUM(C7,C12,C13,C9+C11) -> 5869.3333 | D14: =SUM(D7,D12,D13,D9+D11) -> 5869.3333 | E14: =SUM(E7,E12,E13,E9+E11) -> 5869.3333 | F14: =SUM(F7,F12,F13,F9+F11) -> 5869.3333 | G14: =SUM(G7,G12,G13,G9+G11) -> 5869.3333 | H14: =SUM(H7,H12,H13,H9+H11) -> 5869.3333 | I14: =SUM(I7,I12,I13,I9+I11) -> 5869.3333 | J14: =SUM(J7,J12,J13,J9+J11) -> 5869.3333 | ... N14: =SUM(N7,N12,N13,N9+N11) -> 5869.3333 | O14: =C14*12 -> 70432 | Q14: 650930
B16: PRESUPUESTO DE INGRESOS AÑO 2027
B17: 0.18 | C17: Enero | D17: Febrero | E17: Marzo | F17: Abril | G17: Mayo | H17: Junio | I17: Julio | J17: Agosto | K17: Set | L17: Octubre | M17: Nov | N17: Dici | O17: Año 2
B18: Unidades | C18: 110 | D18: 110 | E18: 110 | F18: 110 | G18: 110 | H18: 110 | I18: 110 | J18: 110 | K18: 110 | L18: 110 | M18: 110 | N18: 110 | O18: =C18*12 -> 1320
B19: Precio unitario (S/30) | C19: =C18*30 -> 3300 | D19: =D18*30 -> 3300 | E19: =E18*30 -> 3300 | F19: =F18*30 -> 3300 | G19: =G18*30 -> 3300 | H19: =H18*30 -> 3300 | I19: =I18*30 -> 3300 | J19: =J18*30 -> 3300 | ... N19: =N18*30 -> 3300 | O19: =C19*12 -> 39600
B20: Clientes con Plan Premium 20% | C20: =C18*0.2 -> 22 | D20: =D18*0.2 -> 22 | E20: =E18*0.2 -> 22 | F20: =F18*0.2 -> 22 | G20: =G18*0.2 -> 22 | H20: =H18*0.2 -> 22 | I20: =I18*0.2 -> 22 | J20: =J18*0.2 -> 22 | ... N20: =N18*0.2 -> 22 | O20: =C20*12 -> 264
B21: Renovación anual de licencia S/120 | C21: =C18*0.12*120/1.44 -> 1100 | D21: =D18*0.12*120/1.44 -> 1100 | E21: =E18*0.12*120/1.44 -> 1100 | F21: =F18*0.12*120/1.44 -> 1100 | G21: =G18*0.12*120/1.44 -> 1100 | H21: =H18*0.12*120/1.44 -> 1100 | I21: =I18*0.12*120/1.44 -> 1100 | J21: =J18*0.12*120/1.44 -> 1100 | ... N21: =N18*0.12*120/1.44 -> 1100 | O21: =C21*12 -> 13200
B22: Tasa de Penetración (Soporte S/ 100) | C22: =C18*0.1*100/1.2 -> 916.66667 | D22: =D18*0.1*100/1.2 -> 916.66667 | E22: =E18*0.1*100/1.2 -> 916.66667 | F22: =F18*0.1*100/1.2 -> 916.66667 | G22: =G18*0.1*100/1.2 -> 916.66667 | H22: =H18*0.1*100/1.2 -> 916.66667 | I22: =I18*0.1*100/1.2 -> 916.66667 | J22: =J18*0.1*100/1.2 -> 916.66667 | ... N22: =N18*0.1*100/1.2 -> 916.66667 | O22: =C22*12 -> 11000
B23: Plan Premium (Premium) S/29 | C23: =C20*29 -> 638 | D23: =D20*29 -> 638 | E23: =E20*29 -> 638 | F23: =F20*29 -> 638 | G23: =G20*29 -> 638 | H23: =H20*29 -> 638 | I23: =I20*29 -> 638 | J23: =J20*29 -> 638 | ... N23: =N20*29 -> 638 | O23: =SUM(C23:N23) -> 7656 | Q23: =O19+#REF!+O21+O22+O23 -> #REF!
B24: Ingresos | C24: =SUM(C19+C22+C21+C23) -> 5954.6667 | D24: =SUM(D19+D22+D21+D23) -> 5954.6667 | E24: =SUM(E19+E22+E21+E23) -> 5954.6667 | F24: =SUM(F19+F22+F21+F23) -> 5954.6667 | G24: =SUM(G19+G22+G21+G23) -> 5954.6667 | H24: =SUM(H19+H22+H21+H23) -> 5954.6667 | I24: =SUM(I19+I22+I21+I23) -> 5954.6667 | J24: =SUM(J19+J22+J21+J23) -> 5954.6667 | ... N24: =SUM(N19+N22+N21+N23) -> 5954.6667 | O24: =SUM(C24:N24) -> 71456
B27: PRESUPUESTO DE INGRESOS AÑO 2028
B28: 0.18 | C28: Enero | D28: Febrero | E28: Marzo | F28: Abril | G28: Mayo | H28: Junio | I28: Julio | J28: Agosto | K28: Set | L28: Octubre | M28: Nov | N28: Dici | O28: Año 3
B29: Unidades | C29: 160 | D29: 160 | E29: 160 | F29: 160 | G29: 160 | H29: 160 | I29: 160 | J29: 160 | K29: 160 | L29: 160 | M29: 160 | N29: 160 | O29: =C29*12 -> 1920
B30: Precio unitario (S/30) | C30: =C29*30 -> 4800 | D30: =D29*30 -> 4800 | E30: =E29*30 -> 4800 | F30: =F29*30 -> 4800 | G30: =G29*30 -> 4800 | H30: =H29*30 -> 4800 | I30: =I29*30 -> 4800 | J30: =J29*30 -> 4800 | ... N30: =N29*30 -> 4800 | O30: =C30*12 -> 57600
B31: Clientes con Plan Premium 20% | C31: =C29*0.2 -> 32 | D31: =D29*0.2 -> 32 | E31: =E29*0.2 -> 32 | F31: =F29*0.2 -> 32 | G31: =G29*0.2 -> 32 | H31: =H29*0.2 -> 32 | I31: =I29*0.2 -> 32 | J31: =J29*0.2 -> 32 | ... N31: =N29*0.2 -> 32 | O31: =C31*12 -> 384
B32: Plan Premium (Premium) S/30 | C32: =C31*30 -> 960 | D32: =D31*30 -> 960 | E32: =E31*30 -> 960 | F32: =F31*30 -> 960 | G32: =G31*30 -> 960 | H32: =H31*30 -> 960 | I32: =I31*30 -> 960 | J32: =J31*30 -> 960 | ... N32: =N31*30 -> 960 | O32: =C32*12 -> 11520
B33: Renovación anual de licencia S/150 | C33: =C29*0.15*150/1.5 -> 2400 | D33: =D29*0.15*150/1.5 -> 2400 | E33: =E29*0.15*150/1.5 -> 2400 | F33: =F29*0.15*150/1.5 -> 2400 | G33: =G29*0.15*150/1.5 -> 2400 | H33: =H29*0.15*150/1.5 -> 2400 | I33: =I29*0.15*150/1.5 -> 2400 | J33: =J29*0.15*150/1.5 -> 2400 | ... N33: =N29*0.15*150/1.5 -> 2400 | O33: =C33*12 -> 28800
B34: Tasa de Penetración (Soporte S/ 100) | C34: =C29*0.1*100/1.2 -> 1333.3333 | D34: =D29*0.1*100/1.2 -> 1333.3333 | E34: =E29*0.1*100/1.2 -> 1333.3333 | F34: =F29*0.1*100/1.2 -> 1333.3333 | G34: =G29*0.1*100/1.2 -> 1333.3333 | H34: =H29*0.1*100/1.2 -> 1333.3333 | I34: =I29*0.1*100/1.2 -> 1333.3333 | J34: =J29*0.1*100/1.2 -> 1333.3333 | ... N34: =N29*0.1*100/1.2 -> 1333.3333 | O34: =C34*12 -> 16000
B35: Ingresos | C35: =C30+C32+C33+C34 -> 9493.3333 | D35: =D30+D32+D33+D34 -> 9493.3333 | E35: =E30+E32+E33+E34 -> 9493.3333 | F35: =F30+F32+F33+F34 -> 9493.3333 | G35: =G30+G32+G33+G34 -> 9493.3333 | H35: =H30+H32+H33+H34 -> 9493.3333 | I35: =I30+I32+I33+I34 -> 9493.3333 | J35: =J30+J32+J33+J34 -> 9493.3333 | ... N35: =N30+N32+N33+N34 -> 9493.3333 | O35: =SUM(C35:N35) -> 113920
C39: 2026 | D39: 2027 | E39: 2028
B40: Proyección de Ventas | C40: =O14 -> 70432 | D40: =O24 -> 71456 | E40: =O35 -> 113920

Sheet 6.4 PRESUPUEST DE eGRESOS
B2: Cuadro 6.4 PRESUPUESTO DE EGRESOS
B4: PRESUPUESTO DE EGRESOS AÑO 2026
C5: Enero | D5: Febrero | E5: Marzo | F5: Abril | G5: Mayo | H5: Junio | I5: Julio | J5: Agosto | K5: Set | L5: Octubre | M5: Nov | N5: Dici | O5: Año 1
B6: Gastos en adquisición de bienes | C6: ='6.2 ESTRUCTURA DE GASTOS'!C9 -> 380 | D6: ='6.2 ESTRUCTURA DE GASTOS'!D9 -> 140 | E6: ='6.2 ESTRUCTURA DE GASTOS'!E9 -> 140 | F6: ='6.2 ESTRUCTURA DE GASTOS'!F9 -> 260 | G6: ='6.2 ESTRUCTURA DE GASTOS'!G9 -> 240 | H6: ='6.2 ESTRUCTURA DE GASTOS'!H9 -> 140 | I6: ='6.2 ESTRUCTURA DE GASTOS'!I9 -> 120 | J6: ='6.2 ESTRUCTURA DE GASTOS'!J9 -> 140 | ... N6: ='6.2 ESTRUCTURA DE GASTOS'!N9 -> 140 | O6: =SUM(C6:N6) -> 2340
B7: Gastos en adquisición de servicios | C7: ='6.1 INVERSION TOTAL'!C24 -> 480 | D7: ='6.1 INVERSION TOTAL'!D24 -> 480 | E7: 560 | F7: 560 | G7: 560 | H7: 560 | I7: 560 | J7: 560 | K7: 560 | L7: 560 | M7: 560 | N7: 560 | O7: =SUM(C7:N7) -> 6560
B8: Gastos en planilla de sueldos | C8: ='6.2 ESTRUCTURA DE GASTOS'!C25 -> 3030 | D8: ='6.2 ESTRUCTURA DE GASTOS'!D25 -> 3030 | E8: ='6.2 ESTRUCTURA DE GASTOS'!E25 -> 3030 | F8: ='6.2 ESTRUCTURA DE GASTOS'!F25 -> 3030 | G8: ='6.2 ESTRUCTURA DE GASTOS'!G25 -> 3030 | H8: ='6.2 ESTRUCTURA DE GASTOS'!H25 -> 3030 | I8: ='6.2 ESTRUCTURA DE GASTOS'!I25 -> 3030 | J8: ='6.2 ESTRUCTURA DE GASTOS'!J25 -> 3030 | ... N8: ='6.2 ESTRUCTURA DE GASTOS'!N25 -> 3030 | O8: =SUM(C8:N8) -> 36360
B9: Egresos | C9: =SUM(C6:C8) -> 3890 | D9: =SUM(D6:D8) -> 3650 | E9: =SUM(E6:E8) -> 3730 | F9: =SUM(F6:F8) -> 3850 | G9: =SUM(G6:G8) -> 3830 | H9: =SUM(H6:H8) -> 3730 | I9: =SUM(I6:I8) -> 3710 | J9: =SUM(J6:J8) -> 3730 | ... N9: =SUM(N6:N8) -> 3730 | O9: =SUM(C9:N9) -> 45260 | Q9: 56032
B11: PRESUPUESTO DE EGRESOS AÑO 2027
C12: Enero | D12: Febrero | E12: Marzo | F12: Abril | G12: Mayo | H12: Junio | I12: Julio | J12: Agosto | K12: Set | L12: Octubre | M12: Nov | N12: Dici | O12: Año 2
B13: Gastos en adquisición de bienes | C13: 212.5 | D13: 212.5 | E13: 212.5 | F13: 212.5 | G13: 212.5 | H13: 212.5 | I13: 212.5 | J13: 212.5 | K13: 212.5 | L13: 212.5 | M13: 212.5 | N13: 212.5 | O13: =SUM(C13:N13) -> 2550
B14: Gastos en adquisición de servicios | C14: 630 | D14: 630 | E14: 630 | F14: 630 | G14: 630 | H14: 630 | I14: 630 | J14: 630 | K14: 630 | L14: 630 | M14: 630 | N14: 630 | O14: =SUM(C14:N14) -> 7560
B15: Gastos en planilla de sueldos | C15: 3068.5 | D15: 3068.5 | E15: 3068.5 | F15: 3068.5 | G15: 3068.5 | H15: 3068.5 | I15: 3068.5 | J15: 3068.5 | K15: 3068.5 | L15: 3068.5 | M15: 3068.5 | N15: 3068.5 | O15: =SUM(C15:N15) -> 36822
B16: Egresos | C16: =C13+C15+C14 -> 3911 | D16: =D13+D15+D14 -> 3911 | E16: =E13+E15+E14 -> 3911 | F16: =F13+F15+F14 -> 3911 | G16: =G13+G15+G14 -> 3911 | H16: =H13+H15+H14 -> 3911 | I16: =I13+I15+I14 -> 3911 | J16: =J13+J15+J14 -> 3911 | ... N16: =N13+N15+N14 -> 3911 | O16: =SUM(C16:N16) -> 46932
B18: PRESUPUESTO DE EGRESOS AÑO 2028
C19: Enero | D19: Febrero | E19: Marzo | F19: Abril | G19: Mayo | H19: Junio | I19: Julio | J19: Agosto | K19: Set | L19: Octubre | M19: Nov | N19: Dici | O19: Año 3
B20: Gastos en adquisición de bienes | C20: 212.5 | D20: 212.5 | E20: 212.5 | F20: 212.5 | G20: 212.5 | H20: 212.5 | I20: 212.5 | J20: 212.5 | K20: 212.5 | L20: 212.5 | M20: 212.5 | N20: 212.5 | O20: =SUM(C20:N20) -> 2550
B21: Gastos en adquisición de servicios | C21: 630 | D21: 630 | E21: 630 | F21: 630 | G21: 630 | H21: 630 | I21: 630 | J21: 630 | K21: 630 | L21: 630 | M21: 630 | N21: 630 | O21: =SUM(C21:N21) -> 7560
B22: Gastos en planilla de sueldos | C22: 3068.5 | D22: 3068.5 | E22: 3068.5 | F22: 3068.5 | G22: 3068.5 | H22: 3068.5 | I22: 3068.5 | J22: 3068.5 | K22: 3068.5 | L22: 3068.5 | M22: 3068.5 | N22: 3068.5 | O22: =SUM(C22:N22) -> 36822
B23: Egresos | C23: =C20+C22+C21 -> 3911 | D23: =D20+D22+D21 -> 3911 | E23: =E20+E22+E21 -> 3911 | F23: =F20+F22+F21 -> 3911 | G23: =G20+G22+G21 -> 3911 | H23: =H20+H22+H21 -> 3911 | I23: =I20+I22+I21 -> 3911 | J23: =J20+J22+J21 -> 3911 | ... N23: =N20+N22+N21 -> 3911 | O23: =SUM(C23:N23) -> 46932
C27: 2026 | D27: 2027 | E27: 2028
B28: Proyección de Egresos | C28: =O9 -> 45260 | D28: =O16 -> 46932 | E28: =O23 -> 46932

Sheet 6.5 FLUJO CAJA MENSUAL 1ER AÑO
A3: FLUJO DE CAJA | B3: MES 0 | C3: MES 1 | D3: MES 2 | E3: MES 3 | F3: MES 4 | G3: MES 5 | H3: MES 6 | I3: MES 7 | J3: MES 8 | K3: MES 9 | L3: MES 10 | M3: MES 11 | N3: MES 12
A4: INGRESOS | B4: 0 | C4: =C5 -> 5869.3333 | D4: =D5 -> 5869.3333 | E4: =E5 -> 5869.3333 | F4: =F5 -> 5869.3333 | G4: =G5 -> 5869.3333 | H4: =H5 -> 5869.3333 | I4: =I5 -> 5869.3333 | J4: =J5 -> 5869.3333 | ... N4: =N5 -> 5869.3333
A5: Ventas | C5: ='6.3 PRESUPUESTO DE INGRESOS'!C14 -> 5869.3333 | D5: ='6.3 PRESUPUESTO DE INGRESOS'!D14 -> 5869.3333 | E5: ='6.3 PRESUPUESTO DE INGRESOS'!E14 -> 5869.3333 | F5: ='6.3 PRESUPUESTO DE INGRESOS'!F14 -> 5869.3333 | G5: ='6.3 PRESUPUESTO DE INGRESOS'!G14 -> 5869.3333 | H5: ='6.3 PRESUPUESTO DE INGRESOS'!H14 -> 5869.3333 | I5: ='6.3 PRESUPUESTO DE INGRESOS'!I14 -> 5869.3333 | J5: ='6.3 PRESUPUESTO DE INGRESOS'!J14 -> 5869.3333 | ... N5: ='6.3 PRESUPUESTO DE INGRESOS'!N14 -> 5869.3333
A6: EGRESOS | B6: ='6.1 INVERSION TOTAL'!D3 -> 19080 | C6: =SUM(C7:C11) -> 7838.6933 | D6: =SUM(D7:D11) -> 7388.6933 | E6: =SUM(E7:E11) -> 7468.6933 | F6: =SUM(F7:F11) -> 7708.6933 | G6: =SUM(G7:G11) -> 7668.6933 | H6: =SUM(H7:H11) -> 7468.6933 | I6: =SUM(I7:I11) -> 7428.6933 | J6: =SUM(J7:J11) -> 7468.6933 | ... N6: =SUM(N7:N11) -> 7468.6933
A7: Producción | C7: ='6.4 PRESUPUEST DE eGRESOS'!C9 -> 3890 | D7: ='6.4 PRESUPUEST DE eGRESOS'!D9 -> 3650 | E7: ='6.4 PRESUPUEST DE eGRESOS'!E9 -> 3730 | F7: ='6.4 PRESUPUEST DE eGRESOS'!F9 -> 3850 | G7: ='6.4 PRESUPUEST DE eGRESOS'!G9 -> 3830 | H7: ='6.4 PRESUPUEST DE eGRESOS'!H9 -> 3730 | I7: ='6.4 PRESUPUEST DE eGRESOS'!I9 -> 3710 | J7: ='6.4 PRESUPUEST DE eGRESOS'!J9 -> 3730 | ... N7: ='6.4 PRESUPUEST DE eGRESOS'!N9 -> 3730
A8: Bienes | C8: ='6.2 ESTRUCTURA DE GASTOS'!C9 -> 380 | D8: ='6.2 ESTRUCTURA DE GASTOS'!D9 -> 140 | E8: ='6.2 ESTRUCTURA DE GASTOS'!E9 -> 140 | F8: ='6.2 ESTRUCTURA DE GASTOS'!F9 -> 260 | G8: ='6.2 ESTRUCTURA DE GASTOS'!G9 -> 240 | H8: ='6.2 ESTRUCTURA DE GASTOS'!H9 -> 140 | I8: ='6.2 ESTRUCTURA DE GASTOS'!I9 -> 120 | J8: ='6.2 ESTRUCTURA DE GASTOS'!J9 -> 140 | ... N8: ='6.2 ESTRUCTURA DE GASTOS'!N9 -> 140
A9: Servicios | C9: ='6.2 ESTRUCTURA DE GASTOS'!C17 -> 480 | D9: ='6.2 ESTRUCTURA DE GASTOS'!D17 -> 510 | E9: ='6.2 ESTRUCTURA DE GASTOS'!E17 -> 510 | F9: ='6.2 ESTRUCTURA DE GASTOS'!F17 -> 510 | G9: ='6.2 ESTRUCTURA DE GASTOS'!G17 -> 510 | H9: ='6.2 ESTRUCTURA DE GASTOS'!H17 -> 510 | I9: ='6.2 ESTRUCTURA DE GASTOS'!I17 -> 510 | J9: ='6.2 ESTRUCTURA DE GASTOS'!J17 -> 510 | ... N9: ='6.2 ESTRUCTURA DE GASTOS'!N17 -> 510
A10: Planilla | C10: ='6.2 ESTRUCTURA DE GASTOS'!C25:N25 -> 3030 | D10: ='6.2 ESTRUCTURA DE GASTOS'!D25:O25 -> 3030 | E10: ='6.2 ESTRUCTURA DE GASTOS'!E25:O25 -> 3030 | F10: ='6.2 ESTRUCTURA DE GASTOS'!F25:P25 -> 3030 | G10: ='6.2 ESTRUCTURA DE GASTOS'!G25:Q25 -> 3030 | H10: ='6.2 ESTRUCTURA DE GASTOS'!H25:R25 -> 3030 | I10: ='6.2 ESTRUCTURA DE GASTOS'!I25:S25 -> 3030 | J10: ='6.2 ESTRUCTURA DE GASTOS'!J25:T25 -> 3030 | K10: ='6.2 ESTRUCTURA DE GASTOS'!K25:U25 -> 3030 | L10: ='6.2 ESTRUCTURA DE GASTOS'!L25:V25 -> 3030 | ... N10: ='6.2 ESTRUCTURA DE GASTOS'!N25:X25 -> 3030
A11: Impuesto a la Renta (1%) | C11: =C5*0.01 -> 58.693333 | D11: =D5*0.01 -> 58.693333 | E11: =E5*0.01 -> 58.693333 | F11: =F5*0.01 -> 58.693333 | G11: =G5*0.01 -> 58.693333 | H11: =H5*0.01 -> 58.693333 | I11: =I5*0.01 -> 58.693333 | J11: =J5*0.01 -> 58.693333 | ... N11: =N5*0.01 -> 58.693333
A12: SALDO | B12: =B4-B6 -> -19080 | C12: =C4-C6 -> -1969.36 | D12: =D4-D6 -> -1519.36 | E12: =E4-E6 -> -1599.36 | F12: =F4-F6 -> -1839.36 | G12: =G4-G6 -> -1799.36 | H12: =H4-H6 -> -1599.36 | I12: =I4-I6 -> -1559.36 | ... N12: =N4-N6 -> -1599.36
A13: P.R. | C13: =B12+C12 -> -21049.36 | D13: =C13+D12 -> -22568.72 | E13: =D13+E12 -> -24168.08 | F13: =E13+F12 -> -26007.44 | G13: =F13+G12 -> -27806.8 | H13: =G13+H12 -> -29406.16 | I13: =H13+I12 -> -30965.52 | J13: =I13+J12 -> -32564.88 | K13: =J13+K12 -> -34404.24 | ... N13: =M13+N12 -> -39402.32
D20: uit | E20: sin no supera el 15, calcular al 10%

Sheet 6.6 FLUJO CAJA PROYECTADO
B3: FLUJO DE CAJA PROYECTADO
B4: FLUJO DE CAJA | C4: AÑO 0 | D4: AÑO 1 | E4: AÑO 2 | F4: AÑO 3
B5: INGRESOS | C5: 0 | D5: =D6 -> 70432 | E5: =E6 -> 71456 | F5: =F6 -> 113920
B6: Ventas | D6: ='6.3 PRESUPUESTO DE INGRESOS'!C40 -> 70432 | E6: ='6.3 PRESUPUESTO DE INGRESOS'!D40 -> 71456 | F6: ='6.3 PRESUPUESTO DE INGRESOS'!E40 -> 113920
B7: EGRESOS | C7: ='6.1 INVERSION TOTAL'!D32 -> 19080 | D7: =SUM(D8:D10) -> 94275 | E7: =SUM(E8:E10) -> 99820.7 | F7: =SUM(F8:F10) -> 101903.71
B8: Producción | D8: ='6.4 PRESUPUEST DE eGRESOS'!O9 -> 45260 | E8: ='6.4 PRESUPUEST DE eGRESOS'!O16 -> 46932 | F8: ='6.4 PRESUPUEST DE eGRESOS'!O23 -> 46932
B9: Gastos administrativos | D9: ='6.2 ESTRUCTURA DE GASTOS'!C37 -> 44790 | E9: ='6.2 ESTRUCTURA DE GASTOS'!D37 -> 46133.7 | F9: ='6.2 ESTRUCTURA DE GASTOS'!E37 -> 47517.711
B10: Impuesto a la Renta | D10: 4225 | E10: 6755 | F10: 7454
B11: SALDO | C11: =C5-C7 -> -19080 | D11: =D5-D7 -> -23843 | E11: =E5-E7 -> -28364.7 | F11: =F5-F7 -> 12016.289
B15: RATIOS
B16: COK | C16: 0.14 | E16: es de una empresa que invierte en mi
B17: VAN | C17: =NPV(C16,C11:F11) -> -47114.013 | E17: lo que gano
B18: TIR | C18: =IRR(C11:F11) -> -0.68257511 | E18: superios al costo de oportunidad
B19: B/C | C19: =C22/C23 -> 0.78287443 | E19: lo que gano
B22: VAN Ing | C22: =NPV(C16,C5:F5) -> 169875.69
B23: VAN Egr | C23: =NPV(C16,C7:F7) -> 216989.7

Sheet Hoja1
C5: en | D5: feb | E5: mar | F5: abr | G5: may | H5: jun | I5: jul | J5: agos | K5: set | L5: oct | M5: nov | N5: dic
C6: 160 | D6: 0 | E6: 0 | F6: 160 | G6: 0 | H6: 0 | I6: 0 | J6: 0 | K6: 160 | L6: 0 | M6: 0 | N6: 0 | O6: =SUM(C6+F6+K6) -> 480
C7: 120 | D7: 0 | E7: 0 | F7: 120 | G7: 120 | H7: 0 | I7: 120 | J7: 0 | K7: 0 | L7: 120 | M7: 120 | N7: 0 | O7: =C7+F7+G7+I7+L7+M7 -> 720
C8: 150 | D8: 150 | E8: 150 | F8: 150 | G8: 0 | H8: 150 | I8: 0 | J8: 150 | K8: 150 | L8: 0 | M8: 150 | N8: 150 | O8: =SUM(C8+D8+E8+F8+H8+J8+K8+M8+N8) -> 1350 | P8: =O8*0.3 -> 405
